{
  "$schema": "https://developer.microsoft.com/json-schemas/fabric/item/report/definition/visualContainer/2.0.0/schema.json",
  "name": "468a18d883190b0a4369",
  "position": {
    "x": 0,
    "y": 0,
    "z": 0,
    "height": 229.9304237824162,
    "width": 597.49525616698293,
    "tabOrder": 0
  },
  "visual": {
    "visualType": "pivotTable",
    "query": {
      "queryState": {
        "Rows": {
          "projections": [
            {
              "field": {
                "Column": {
                  "Expression": {
                    "SourceRef": {
                      "Entity": "Calendar Lookup"
                    }
                  },
                  "Property": "Year"
                }
              },
              "queryRef": "Calendar Lookup.Year",
              "nativeQueryRef": "Year",
              "active": true
            },
            {
              "field": {
                "Column": {
                  "Expression": {
                    "SourceRef": {
                      "Entity": "Calendar Lookup"
                    }
                  },
                  "Property": "Start of Month"
                }
              },
              "queryRef": "Calendar Lookup.Start of Month",
              "nativeQueryRef": "Start of Month",
              "active": true
            }
          ]
        },
        "Values": {
          "projections": [
            {
              "field": {
                "Measure": {
                  "Expression": {
                    "SourceRef": {
                      "Entity": "Measure Table"
                    }
                  },
                  "Property": "Total Orders"
                }
              },
              "queryRef": "Measure Table.Total Orders",
              "nativeQueryRef": "Total Orders"
            }
          ]
        }
      }
    },
    "expansionStates": [
      {
        "roles": [
          "Rows"
        ],
        "levels": [
          {
            "queryRefs": [
              "Calendar Lookup.Year"
            ],
            "isCollapsed": true,
            "identityKeys": [
              {
                "Column": {
                  "Expression": {
                    "SourceRef": {
                      "Entity": "Calendar Lookup"
                    }
                  },
                  "Property": "Year"
                }
              }
            ],
            "isPinned": true
          },
          {
            "queryRefs": [
              "Calendar Lookup.Start of Month"
            ],
            "isCollapsed": true,
            "identityKeys": [
              {
                "Column": {
                  "Expression": {
                    "SourceRef": {
                      "Entity": "Calendar Lookup"
                    }
                  },
                  "Property": "Start of Month"
                }
              }
            ],
            "isPinned": true
          }
        ],
        "root": {
          "children": [
            {
              "identityValues": [
                {
                  "Literal": {
                    "Value": "2020L"
                  }
                }
              ],
              "isToggled": true
            },
            {
              "identityValues": [
                {
                  "Literal": {
                    "Value": "2022L"
                  }
                }
              ],
              "isToggled": true
            }
          ]
        }
      }
    ],
    "drillFilterOtherVisuals": true
  }
}